recastai/__init__.py
recastai/client.py
recastai/utils.py
recastai/apis/__init__.py
recastai/apis/errors.py
recastai/apis/build/__init__.py
recastai/apis/build/build.py
recastai/apis/build/dialog_conversation.py
recastai/apis/build/dialog_message.py
recastai/apis/build/dialog_response.py
recastai/apis/build/utils.py
recastai/apis/connect/__init__.py
recastai/apis/connect/connect.py
recastai/apis/connect/message.py
recastai/apis/connect/utils.py
recastai/apis/connect/models/__init__.py
recastai/apis/connect/models/message.py
recastai/apis/request/__init__.py
recastai/apis/request/analyse.py
recastai/apis/request/converse.py
recastai/apis/request/request.py
recastai/apis/request/utils.py
recastai/apis/request/models/__init__.py
recastai/apis/request/models/action.py
recastai/apis/request/models/conversation.py
recastai/apis/request/models/entity.py
recastai/apis/request/models/intent.py
recastai/apis/request/models/response.py
recastai-4.0.0.dist-info/METADATA
recastai-4.0.0.dist-info/RECORD
recastai-4.0.0.dist-info/WHEEL
recastai-4.0.0.dist-info/top_level.txt
tests/__init__.py
tests/recastai/__init__.py
tests/recastai/test_recastai.py
