Metadata-Version: 1.0
Name: recastai
Version: 4.0.0
Summary: Recast.AI official SDK for python
Home-page: https://github.com/RecastAI/sdk-python
Author: Paul Renvoise
Author-email: paul.renvoise@recast.ai
License: MIT
Keywords: recastai bot nlp
Platform: UNKNOWN
